[
  {
    "id": "REGINEV.14",
    "brand": "GIULIA",
    "title": "Decoltè Giulia Nude Charol",
    "size": null,
    "availability": "in_stock",
    "price": "75.00 EUR",
    "sale_price": "75.00 EUR",
    "color": "ROSA",
    "gender": "Donna",
    "category": "DECOLLETE",
    "season": "E23",
    "image": "https://www.langolo-calzature.it/media/catalog/product/r/e/reginev.14-0001.jpg",
    "link": "https://www.langolo-calzature.it/it/brand/giulia/decolte-giulia-nude-charol"
  },
  {
    "id": "HANDBAG.14",
    "brand": "GIULIA",
    "title": "Handbag Nude Charol",
    "size": null,
    "availability": "in_stock",
    "price": "29.00 EUR",
    "sale_price": "29.00 EUR",
    "color": "ROSA",
    "gender": "Donna",
    "category": "ACCESSORI",
    "season": "E24",
    "image": "https://www.langolo-calzature.it/media/catalog/product/h/a/handbag.14-0000.jpg",
    "link": "https://www.langolo-calzature.it/it/brand/giulia/handbag-nude-charol"
  },
  {
    "id": "HANDBAG.18",
    "brand": "GIULIA",
    "title": "Handbag Shade Ante",
    "size": null,
    "availability": "in_stock",
    "price": "29.00 EUR",
    "sale_price": "29.00 EUR",
    "color": "GIALLO",
    "gender": "Donna",
    "category": "ACCESSORI",
    "season": "E24",
    "image": "https://www.langolo-calzature.it/media/catalog/product/h/a/handbag.18-0000.jpg",
    "link": "https://www.langolo-calzature.it/it/brand/giulia/handbag-shade-ante"
  },
  {
    "id": "HANDBAG.ANI",
    "brand": "GIULIA",
    "title": "Handbag Arena Mombasa",
    "size": null,
    "availability": "in_stock",
    "price": "29.00 EUR",
    "sale_price": "29.00 EUR",
    "color": "ANIMALIER",
    "gender": "Donna",
    "category": "ACCESSORI",
    "season": "E24",
    "image": "https://www.langolo-calzature.it/media/catalog/product/h/a/handbag.ani-0000.jpg",
    "link": "https://www.langolo-calzature.it/it/brand/giulia/handbag-arena-mombasa"
  },
  {
    "id": "HANDBAG.LEO",
    "brand": "GIULIA",
    "title": "Handbag Arena Animalier",
    "size": null,
    "availability": "in_stock",
    "price": "29.00 EUR",
    "sale_price": "29.00 EUR",
    "color": "ANIMALIER",
    "gender": "Donna",
    "category": "ACCESSORI",
    "season": "E24",
    "image": "https://www.langolo-calzature.it/media/catalog/product/h/a/handbag.leo-0000.jpg",
    "link": "https://www.langolo-calzature.it/it/brand/giulia/handbag-arena-leopardo"
  },
  {
    "id": "HANDBAG.11",
    "brand": "GIULIA",
    "title": "Handbag Bermellon Charol",
    "size": null,
    "availability": "in_stock",
    "price": "29.00 EUR",
    "sale_price": "29.00 EUR",
    "color": "ROSSO",
    "gender": "Donna",
    "category": "ACCESSORI",
    "season": "E24",
    "image": "https://www.langolo-calzature.it/media/catalog/product/h/a/handbag.11-0000.jpg",
    "link": "https://www.langolo-calzature.it/it/brand/giulia/handbag-bermellon-charol"
  },
  {
    "id": "HANDBAG.09",
    "brand": "GIULIA",
    "title": "Handbag Nude Ante",
    "size": null,
    "availability": "in_stock",
    "price": "29.00 EUR",
    "sale_price": "29.00 EUR",
    "color": "BEIGE",
    "gender": "Donna",
    "category": "ACCESSORI",
    "season": "E24",
    "image": "https://www.langolo-calzature.it/media/catalog/product/h/a/handbag.09-0001.jpg",
    "link": "https://www.langolo-calzature.it/it/brand/giulia/handbag-nude-ante"
  },
  {
    "id": "GIULIA5.01",
    "brand": "GIULIA",
    "title": "Decoltè a punta nera con tacco 5",
    "size": null,
    "availability": "in_stock",
    "price": "75.00 EUR",
    "sale_price": "75.00 EUR",
    "color": "NERO",
    "gender": "Donna",
    "category": "DECOLLETE",
    "season": "E24",
    "image": "https://www.langolo-calzature.it/media/catalog/product/g/i/giulia5.01-0001.jpg",
    "link": "https://www.langolo-calzature.it/it/brand/giulia/decolte-a-punta-nera-con-tacco-5"
  },
  {
    "id": "HANDBAGP.01",
    "brand": "GIULIA",
    "title": "Handbag Napa Nero",
    "size": null,
    "availability": "in_stock",
    "price": "29.00 EUR",
    "sale_price": "29.00 EUR",
    "color": "NERO",
    "gender": "Donna",
    "category": "ACCESSORI",
    "season": "E24",
    "image": "https://www.langolo-calzature.it/media/catalog/product/h/a/handbagp.01-0001.jpg",
    "link": "https://www.langolo-calzature.it/it/brand/giulia/handbag-napa-nero"
  },
  {
    "id": "GIULIAT8C.26",
    "brand": "GIULIA",
    "title": "Decoltè Ante Green",
    "size": null,
    "availability": "in_stock",
    "price": "75.00 EUR",
    "sale_price": "75.00 EUR",
    "color": "VERDE",
    "gender": "Donna",
    "category": "DECOLLETE",
    "season": "E22",
    "image": "https://www.langolo-calzature.it/media/catalog/product/g/i/giuliat8c.26-0001.jpg",
    "link": "https://www.langolo-calzature.it/it/brand/giulia/decolte-ante-green"
  },
  {
    "id": "GIULIAT8CF.14",
    "brand": "GIULIA",
    "title": "Decoltè Ante Fresa",
    "size": null,
    "availability": "in_stock",
    "price": "75.00 EUR",
    "sale_price": "75.00 EUR",
    "color": "ROSA",
    "gender": "Donna",
    "category": "DECOLLETE",
    "season": "E24",
    "image": "https://www.langolo-calzature.it/media/catalog/product/g/i/giuliat8cf.14-0001.jpg",
    "link": "https://www.langolo-calzature.it/it/brand/giulia/decolte-ante-fresa"
  },
  {
    "id": "HANDBAGS.06",
    "brand": "GIULIA",
    "title": "Pochette Ante Marino",
    "size": null,
    "availability": "in_stock",
    "price": "29.00 EUR",
    "sale_price": "29.00 EUR",
    "color": "BLU",
    "gender": "Donna",
    "category": "ACCESSORI",
    "season": "E24",
    "image": "https://www.langolo-calzature.it/media/catalog/product/h/a/handbags.06-0001.jpg",
    "link": "https://www.langolo-calzature.it/it/brand/giulia/pochette-ante-marino"
  },
  {
    "id": "HANDBAG2.19",
    "brand": "GIULIA",
    "title": "Handbag Burdeos Ante",
    "size": null,
    "availability": "in_stock",
    "price": "29.00 EUR",
    "sale_price": "29.00 EUR",
    "color": "ROSSO",
    "gender": "Donna",
    "category": "ACCESSORI",
    "season": "E24",
    "image": "https://www.langolo-calzature.it/media/catalog/product/h/a/handbag2.19-0000.jpg",
    "link": "https://www.langolo-calzature.it/it/brand/giulia/handbag-burdeos-ante"
  },
  {
    "id": "HANDBAG3.06",
    "brand": "GIULIA",
    "title": "Handbag Napa Marino",
    "size": null,
    "availability": "in_stock",
    "price": "29.00 EUR",
    "sale_price": "29.00 EUR",
    "color": "BLU",
    "gender": "Donna",
    "category": "ACCESSORI",
    "season": "E24",
    "image": "https://www.langolo-calzature.it/media/catalog/product/h/a/handbag3.06-0000.jpg",
    "link": "https://www.langolo-calzature.it/it/brand/giulia/handbag-napa-marino"
  },
  {
    "id": "G8SHANY.08",
    "brand": "GIULIA",
    "title": "Scarpa a punta Novia con slingback",
    "size": null,
    "availability": "in_stock",
    "price": "75.00 EUR",
    "sale_price": "75.00 EUR",
    "color": "BIANCO",
    "gender": "Donna",
    "category": "SANDALI",
    "season": "E23",
    "image": "https://www.langolo-calzature.it/media/catalog/product/g/8/g8shany.08-0001.jpg",
    "link": "https://www.langolo-calzature.it/it/brand/giulia/scarpa-a-punta-novia-con-slingback"
  },
  {
    "id": "G8SHANY.15",
    "brand": "GIULIA",
    "title": "Scarpa a punta Light Gold con slingback",
    "size": null,
    "availability": "in_stock",
    "price": "75.00 EUR",
    "sale_price": "75.00 EUR",
    "color": "ORO",
    "gender": "Donna",
    "category": "SANDALI",
    "season": "E23",
    "image": "https://www.langolo-calzature.it/media/catalog/product/g/8/g8shany.15-0001.jpg",
    "link": "https://www.langolo-calzature.it/it/brand/giulia/scarpa-a-punta-light-gold-con-slingback"
  },
  {
    "id": "GIULIA8.08",
    "brand": "GIULIA",
    "title": "Decoltè Novia",
    "size": null,
    "availability": "in_stock",
    "price": "75.00 EUR",
    "sale_price": "75.00 EUR",
    "color": "BIANCO",
    "gender": "Donna",
    "category": "DECOLLETE",
    "season": "E23",
    "image": "https://www.langolo-calzature.it/media/catalog/product/g/i/giulia8.08-0001.jpg",
    "link": "https://www.langolo-calzature.it/it/brand/giulia/decolte-novia"
  },
  {
    "id": "GIULIA8.14",
    "brand": "GIULIA",
    "title": "Decoltè Charol Fluor Fuxia",
    "size": null,
    "availability": "in_stock",
    "price": "75.00 EUR",
    "sale_price": "75.00 EUR",
    "color": "ROSA",
    "gender": "Donna",
    "category": "DECOLLETE",
    "season": "E23",
    "image": "https://www.langolo-calzature.it/media/catalog/product/g/i/giulia8.14-0001.jpg",
    "link": "https://www.langolo-calzature.it/it/brand/giulia/decolte-charol-fluor-fuxia"
  },
  {
    "id": "G8GIULIA8.50",
    "brand": "GIULIA",
    "title": "Decoltè Ante Lilas",
    "size": null,
    "availability": "in_stock",
    "price": "75.00 EUR",
    "sale_price": "75.00 EUR",
    "color": "VIOLA",
    "gender": "Donna",
    "category": "DECOLLETE",
    "season": "E23",
    "image": "https://www.langolo-calzature.it/media/catalog/product/g/8/g8giulia8.50-0001.jpg",
    "link": "https://www.langolo-calzature.it/it/brand/giulia/decolte-ante-lilas"
  },
  {
    "id": "REGINEP.15",
    "brand": "GIULIA",
    "title": "Decoltè laminata oro",
    "size": null,
    "availability": "in_stock",
    "price": "75.00 EUR",
    "sale_price": "75.00 EUR",
    "color": "ORO",
    "gender": "Donna",
    "category": "DECOLLETE",
    "season": "E24",
    "image": "https://www.langolo-calzature.it/media/catalog/product/r/e/reginep.15-0001.jpg",
    "link": "https://www.langolo-calzature.it/it/catalog/product/view/id/682808/s/decolte-laminata-oro/category/304/"
  },
  {
    "id": "REGINEP.16",
    "brand": "GIULIA",
    "title": "Decoltè laminata argento",
    "size": null,
    "availability": "in_stock",
    "price": "75.00 EUR",
    "sale_price": "75.00 EUR",
    "color": "ARGENTO",
    "gender": "Donna",
    "category": "DECOLLETE",
    "season": "E24",
    "image": "https://www.langolo-calzature.it/media/catalog/product/r/e/reginep.16-0001.jpg",
    "link": "https://www.langolo-calzature.it/it/catalog/product/view/id/682809/s/decolte-laminata-argento/category/304/"
  },
  {
    "id": "GIULIA8MAR.11",
    "brand": "GIULIA",
    "title": "Decoltè Ante Marlboro",
    "size": null,
    "availability": "in_stock",
    "price": "75.00 EUR",
    "sale_price": "75.00 EUR",
    "color": "ROSSO",
    "gender": "Donna",
    "category": "DECOLLETE",
    "season": "E24",
    "image": "https://www.langolo-calzature.it/media/catalog/product/g/i/giulia8mar.11-0001.jpg",
    "link": "https://www.langolo-calzature.it/it/catalog/product/view/id/683413/s/decolte-ante-marlboro/category/304/"
  },
  {
    "id": "HANDBAG.01",
    "brand": "GIULIA",
    "title": "Handbag Negro Ante",
    "size": null,
    "availability": "in_stock",
    "price": "29.00 EUR",
    "sale_price": "29.00 EUR",
    "color": "NERO",
    "gender": "Donna",
    "category": "ACCESSORI",
    "season": "E24",
    "image": "https://www.langolo-calzature.it/media/catalog/product/h/a/handbag.01-0000.jpg",
    "link": "https://www.langolo-calzature.it/it/catalog/product/view/id/691857/s/handbag-negro-ante/category/304/"
  },
  {
    "id": "HANDBAG.06",
    "brand": "GIULIA",
    "title": "Handbag Ante Francia",
    "size": null,
    "availability": "in_stock",
    "price": "29.00 EUR",
    "sale_price": "29.00 EUR",
    "color": "BLU",
    "gender": "Donna",
    "category": "ACCESSORI",
    "season": "E24",
    "image": "https://www.langolo-calzature.it/media/catalog/product/h/a/handbag.06-0001.jpg",
    "link": "https://www.langolo-calzature.it/it/catalog/product/view/id/691858/s/handbag-ante-francia/category/304/"
  },
  {
    "id": "HANDBAG2.09",
    "brand": "GIULIA",
    "title": "Handbag Gamo Ante",
    "size": null,
    "availability": "in_stock",
    "price": "29.00 EUR",
    "sale_price": "29.00 EUR",
    "color": "BEIGE",
    "gender": "Donna",
    "category": "ACCESSORI",
    "season": "E24",
    "image": "https://www.langolo-calzature.it/media/catalog/product/h/a/handbag2.09-0000.jpg",
    "link": "https://www.langolo-calzature.it/it/catalog/product/view/id/691860/s/handbag-gamo-ante/category/304/"
  },
  {
    "id": "G8SHANY.14",
    "brand": "GIULIA",
    "title": "Scarpa a punta Charol Nude con slingback",
    "size": null,
    "availability": "in_stock",
    "price": "75.00 EUR",
    "sale_price": "75.00 EUR",
    "color": "ROSA",
    "gender": "Donna",
    "category": "SANDALI",
    "season": "E23",
    "image": "https://www.langolo-calzature.it/media/catalog/product/g/8/g8shany.14-0001.jpg",
    "link": "https://www.langolo-calzature.it/it/catalog/product/view/id/694584/s/scarpa-a-punta-charol-nude-con-slingback/category/304/"
  },
  {
    "id": "GIULIAT8.16",
    "brand": "GIULIA",
    "title": "Decoltè Argento in Ecopelle",
    "size": null,
    "availability": "in_stock",
    "price": "75.00 EUR",
    "sale_price": "75.00 EUR",
    "color": "ARGENTO",
    "gender": "Donna",
    "category": "DECOLLETE",
    "season": "E24",
    "image": "https://www.langolo-calzature.it/media/catalog/product/g/i/giuliat8.16-0001.jpg",
    "link": "https://www.langolo-calzature.it/it/catalog/product/view/id/695488/s/decolte-argento-in-ecopelle/category/304/"
  },
  {
    "id": "G1MOCK.02",
    "brand": "GIULIA",
    "title": "Mocassino Classico in Pelle Marrone",
    "size": null,
    "availability": "in_stock",
    "price": "79.00 EUR",
    "sale_price": "79.00 EUR",
    "color": "MARRONE",
    "gender": "Donna",
    "category": "MOCASSINI E SCARPE SENZA LACCI",
    "season": "E25",
    "image": "https://www.langolo-calzature.it/media/catalog/product/g/1/g1mock.02-0001.jpg",
    "link": "https://www.langolo-calzature.it/it/catalog/product/view/id/713549/s/mocassino-classico-in-pelle-marrone/category/423/"
  },
  {
    "id": "G1MOCK.06",
    "brand": "GIULIA",
    "title": "Mocassino Classico in Pelle Blu",
    "size": null,
    "availability": "in_stock",
    "price": "79.00 EUR",
    "sale_price": "79.00 EUR",
    "color": "BLU",
    "gender": "Donna",
    "category": "MOCASSINI E SCARPE SENZA LACCI",
    "season": "E25",
    "image": "https://www.langolo-calzature.it/media/catalog/product/g/1/g1mock.06-0001.jpg",
    "link": "https://www.langolo-calzature.it/it/catalog/product/view/id/713550/s/mocassino-classico-in-pelle-blu/category/423/"
  },
  {
    "id": "G1MOCK.09",
    "brand": "GIULIA",
    "title": "Mocassini Classici in Camoscio Cuoio",
    "size": null,
    "availability": "in_stock",
    "price": "79.00 EUR",
    "sale_price": "79.00 EUR",
    "color": "BEIGE",
    "gender": "Donna",
    "category": "MOCASSINI E SCARPE SENZA LACCI",
    "season": "E25",
    "image": "https://www.langolo-calzature.it/media/catalog/product/g/1/g1mock.09-0001.jpg",
    "link": "https://www.langolo-calzature.it/it/catalog/product/view/id/713551/s/mocassini-classici-in-camoscio-cuoio/category/423/"
  },
  {
    "id": "G1MOCK.11",
    "brand": "GIULIA",
    "title": "Mocassino Classico in Camoscio Rosso",
    "size": null,
    "availability": "in_stock",
    "price": "79.00 EUR",
    "sale_price": "79.00 EUR",
    "color": "ROSSO",
    "gender": "Donna",
    "category": "MOCASSINI E SCARPE SENZA LACCI",
    "season": "E25",
    "image": "https://www.langolo-calzature.it/media/catalog/product/g/1/g1mock.11-0001.jpg",
    "link": "https://www.langolo-calzature.it/it/catalog/product/view/id/713552/s/mocassino-classico-in-camoscio-rosso/category/423/"
  },
  {
    "id": "G1MOCK.18",
    "brand": "GIULIA",
    "title": "Mocassino Classico in Camoscio Giallo",
    "size": null,
    "availability": "in_stock",
    "price": "79.00 EUR",
    "sale_price": "79.00 EUR",
    "color": "GIALLO",
    "gender": "Donna",
    "category": "MOCASSINI E SCARPE SENZA LACCI",
    "season": "E25",
    "image": "https://www.langolo-calzature.it/media/catalog/product/g/1/g1mock.18-0001.jpg",
    "link": "https://www.langolo-calzature.it/it/catalog/product/view/id/713553/s/mocassino-classico-in-camoscio-giallo/category/423/"
  },
  {
    "id": "G1MOCK.26",
    "brand": "GIULIA",
    "title": "Mocassini Clasici in Camoscio Beige",
    "size": null,
    "availability": "in_stock",
    "price": "79.00 EUR",
    "sale_price": "79.00 EUR",
    "color": "VERDE",
    "gender": "Donna",
    "category": "MOCASSINI E SCARPE SENZA LACCI",
    "season": "E25",
    "image": "https://www.langolo-calzature.it/media/catalog/product/g/1/g1mock.26-0001.jpg",
    "link": "https://www.langolo-calzature.it/it/catalog/product/view/id/713554/s/mocassini-clasici-in-camoscio-beige/category/423/"
  },
  {
    "id": "G1MOCK.50",
    "brand": "GIULIA",
    "title": "Mocassino Classico in Camoscio Lilla",
    "size": null,
    "availability": "in_stock",
    "price": "79.00 EUR",
    "sale_price": "79.00 EUR",
    "color": "VIOLA",
    "gender": "Donna",
    "category": "MOCASSINI E SCARPE SENZA LACCI",
    "season": "E25",
    "image": "https://www.langolo-calzature.it/media/catalog/product/g/1/g1mock.50-0001.jpg",
    "link": "https://www.langolo-calzature.it/it/catalog/product/view/id/713555/s/mocassino-classico-in-camoscio-lilla/category/423/"
  },
  {
    "id": "G1MOCK6.06",
    "brand": "GIULIA",
    "title": "Mocassino Classico in Camoscio Blu Notte",
    "size": null,
    "availability": "in_stock",
    "price": "79.00 EUR",
    "sale_price": "79.00 EUR",
    "color": "BLU",
    "gender": "Donna",
    "category": "MOCASSINI E SCARPE SENZA LACCI",
    "season": "E25",
    "image": "https://www.langolo-calzature.it/media/catalog/product/g/1/g1mock6.06-0001.jpg",
    "link": "https://www.langolo-calzature.it/it/catalog/product/view/id/713556/s/mocassino-classico-in-camoscio-blu-notte/category/423/"
  }
]