[
  {
    "id": "07433.01",
    "brand": "SILK-O&#039;",
    "title": "Texano Basso in Pelle Nero con Zip",
    "size": null,
    "availability": "in_stock",
    "price": "149.00 EUR",
    "sale_price": "119.00 EUR",
    "color": "NERO",
    "gender": "Donna",
    "category": "TRONCHETTI",
    "season": "E24",
    "image": "https://www.langolo-calzature.it/media/catalog/product/0/7/07433.01-0001.jpg",
    "link": "https://www.langolo-calzature.it/it/catalog/product/view/id/696139/s/texano-basso-in-pelle-nero-con-zip/category/466/"
  },
  {
    "id": "1765R.01",
    "brand": "SILK-O&#039;",
    "title": "Texano Alto in Pelle Nera",
    "size": null,
    "availability": "in_stock",
    "price": "169.00 EUR",
    "sale_price": "135.00 EUR",
    "color": "NERO",
    "gender": "Donna",
    "category": "STIVALI ALTI",
    "season": "E24",
    "image": "https://www.langolo-calzature.it/media/catalog/product/1/7/1765r.01-0001.jpg",
    "link": "https://www.langolo-calzature.it/it/catalog/product/view/id/696142/s/texano-alto-in-pelle-nera/category/488/"
  },
  {
    "id": "PT06.01",
    "brand": "SILK-O&#039;",
    "title": "Texano Basso in Pelle Nero",
    "size": null,
    "availability": "in_stock",
    "price": "149.00 EUR",
    "sale_price": "125.00 EUR",
    "color": "NERO",
    "gender": "Donna",
    "category": "TRONCHETTI",
    "season": "E24",
    "image": "https://www.langolo-calzature.it/media/catalog/product/p/t/pt06.01-0001.jpg",
    "link": "https://www.langolo-calzature.it/it/catalog/product/view/id/696157/s/texano-basso-in-pelle-nero/category/466/"
  },
  {
    "id": "TX10.09",
    "brand": "SILK-O&#039;",
    "title": "Stivali Texani Beige in Vera Pelle Scamosciata",
    "size": null,
    "availability": "in_stock",
    "price": "139.00 EUR",
    "sale_price": "139.00 EUR",
    "color": "BEIGE",
    "gender": "Donna",
    "category": "STIVALI ALTI",
    "season": "E25",
    "image": "https://www.langolo-calzature.it/media/catalog/product/t/x/tx10.09-0001.jpg",
    "link": "https://www.langolo-calzature.it/it/catalog/product/view/id/720946/s/stivali-texani-beige-in-vera-pelle-scamosciata/category/246/"
  },
  {
    "id": "TX37.09",
    "brand": "SILK-O&#039;",
    "title": "Texani Donna Beige In Vera Pelle Scamosciata",
    "size": null,
    "availability": "in_stock",
    "price": "139.00 EUR",
    "sale_price": "139.00 EUR",
    "color": "BEIGE",
    "gender": "Donna",
    "category": "TRONCHETTI",
    "season": "E25",
    "image": "https://www.langolo-calzature.it/media/catalog/product/t/x/tx37.09-0001.jpg",
    "link": "https://www.langolo-calzature.it/it/catalog/product/view/id/720947/s/texani-donna-beige-in-vera-pelle-scamosciata/category/287/"
  },
  {
    "id": "TX34.02",
    "brand": "SILK-O&#039;",
    "title": "Tronchetto Texano in Camoscio Cuoio",
    "size": null,
    "availability": "in_stock",
    "price": "129.00 EUR",
    "sale_price": "129.00 EUR",
    "color": "MARRONE",
    "gender": "Donna",
    "category": "TRONCHETTI",
    "season": "E25",
    "image": "https://www.langolo-calzature.it/media/catalog/product/t/x/tx34.02-0001.jpg",
    "link": "https://www.langolo-calzature.it/it/catalog/product/view/id/721102/s/tronchetto-texano-in-camoscio-cuoio/category/246/"
  }
]